{
  "audiovisual_files": {
    "0e4033bf-426b-4e88-a11f-85cd445c1966": {
      "label": "LAPR1974_01_24",
      "is_offline": false,
      "file_url": "https://utexas.box.com/shared/static/9nl029bi8jaerf0v04c5mi5ha42ytksn.mp3",
      "duration": 1681,
      "caption_set": []
    }
  },
  "auto_generate_web_page": false,
  "description": [
    {
      "type": "paragraph",
      "children": [
        {
          "text": ""
        }
      ]
    }
  ],
  "citation": "",
  "item_type": "Audio",
  "label": "LAPR1974_01_24",
  "created_at": "2025-04-29T16:37:41.359Z",
  "created_by": "rpr88",
  "updated_at": "2025-04-29T16:50:22.632Z",
  "updated_by": "rpr88"
}